<?xml version="1.0" encoding="UTF-8"?>
<con:soapui-project id="8b6d6d1e-f588-4fd3-9e62-85b17dc460d4" activeEnvironment="Default" name="IS_Lab5_SoapUI" resourceRoot="" soapui-version="5.9.1" xmlns:con="http://eviware.com/soapui/config"><con:settings/><con:interface xsi:type="con:WsdlInterface" id="5781d308-869a-456e-b722-bb58acab7f16" wsaVersion="NONE" name="SOAPDemoSoap" type="wsdl" bindingName="{http://tempuri.org}SOAPDemoSoap" soapVersion="1_1" anonymous="optional" definition="https://www.crcind.com/csp/samples/SOAP.Demo.CLS?WSDL=1" xmlns:xsi="http://www.w3.org/2001/XMLSchema-instance"><con:settings/><con:definitionCache type="TEXT" rootPart="https://www.crcind.com/csp/samples/SOAP.Demo.CLS?WSDL=1"><con:part><con:url>https://www.crcind.com/csp/samples/SOAP.Demo.CLS?WSDL=1</con:url><con:content><![CDATA[<definitions targetNamespace="http://tempuri.org" xmlns="http://schemas.xmlsoap.org/wsdl/" xmlns:SOAP-ENC="http://schemas.xmlsoap.org/soap/encoding/" xmlns:mime="http://schemas.xmlsoap.org/wsdl/mime/" xmlns:s="http://www.w3.org/2001/XMLSchema" xmlns:s0="http://tempuri.org" xmlns:soap="http://schemas.xmlsoap.org/wsdl/soap/" xmlns:wsdl="http://schemas.xmlsoap.org/wsdl/" xmlns:xsi="http://www.w3.org/2001/XMLSchema-instance">
  <types>
    <s:schema elementFormDefault="qualified" targetNamespace="http://tempuri.org">
      <s:import namespace="http://tempuri.org/ByNameDataSet" schemaLocation="https://www.crcind.com:443/csp/samples/SOAP.ByNameDataSet.cls?XSD"/>
      <s:import namespace="http://tempuri.org/QueryByName_DataSet" schemaLocation="https://www.crcind.com:443/csp/samples/SOAP.Demo.QueryByName.DS.cls?XSD"/>
      <s:element name="AddInteger">
        <s:complexType>
          <s:sequence>
            <s:element minOccurs="0" name="Arg1" type="s:long"/>
            <s:element minOccurs="0" name="Arg2" type="s:long"/>
          </s:sequence>
        </s:complexType>
      </s:element>
      <s:element name="AddIntegerResponse">
        <s:complexType>
          <s:sequence>
            <s:element name="AddIntegerResult" type="s:long"/>
          </s:sequence>
        </s:complexType>
      </s:element>
      <s:element name="DivideInteger">
        <s:complexType>
          <s:sequence>
            <s:element minOccurs="0" name="Arg1" type="s:long"/>
            <s:element minOccurs="0" name="Arg2" type="s:long"/>
          </s:sequence>
        </s:complexType>
      </s:element>
      <s:element name="DivideIntegerResponse">
        <s:complexType>
          <s:sequence>
            <s:element name="DivideIntegerResult" type="s:long"/>
          </s:sequence>
        </s:complexType>
      </s:element>
      <s:element name="FindPerson">
        <s:complexType>
          <s:sequence>
            <s:element minOccurs="0" name="id" type="s:string"/>
          </s:sequence>
        </s:complexType>
      </s:element>
      <s:element name="FindPersonResponse">
        <s:complexType>
          <s:sequence>
            <s:element name="FindPersonResult" type="s0:Person"/>
          </s:sequence>
        </s:complexType>
      </s:element>
      <s:complexType name="Employee">
        <s:complexContent>
          <s:extension base="s0:Person">
            <s:sequence>
              <s:element minOccurs="0" name="Title">
                <s:simpleType>
                  <s:restriction base="s:string">
                    <s:maxLength value="50"/>
                  </s:restriction>
                </s:simpleType>
              </s:element>
              <s:element minOccurs="0" name="Salary">
                <s:simpleType>
                  <s:restriction base="s:long">
                    <s:maxInclusive value="100000"/>
                    <s:minInclusive value="0"/>
                  </s:restriction>
                </s:simpleType>
              </s:element>
              <s:element minOccurs="0" name="Notes" type="s:string"/>
              <s:element minOccurs="0" name="Picture" type="s:base64Binary"/>
            </s:sequence>
          </s:extension>
        </s:complexContent>
      </s:complexType>
      <s:complexType name="Person">
        <s:sequence>
          <s:element name="Name" type="s:string"/>
          <s:element name="SSN" type="s:string"/>
          <s:element minOccurs="0" name="DOB" type="s:date"/>
          <s:element minOccurs="0" name="Home" type="s0:Address"/>
          <s:element minOccurs="0" name="Office" type="s0:Address"/>
          <s:element minOccurs="0" name="Spouse" type="s0:Person"/>
          <s:element minOccurs="0" name="FavoriteColors" type="s0:ArrayOfFavoriteColorsItemString"/>
          <s:element minOccurs="0" name="Age" type="s:long"/>
        </s:sequence>
      </s:complexType>
      <s:complexType name="Address">
        <s:sequence>
          <s:element minOccurs="0" name="Street">
            <s:simpleType>
              <s:restriction base="s:string">
                <s:maxLength value="80"/>
              </s:restriction>
            </s:simpleType>
          </s:element>
          <s:element minOccurs="0" name="City">
            <s:simpleType>
              <s:restriction base="s:string">
                <s:maxLength value="80"/>
              </s:restriction>
            </s:simpleType>
          </s:element>
          <s:element minOccurs="0" name="State">
            <s:simpleType>
              <s:restriction base="s:string">
                <s:maxLength value="2"/>
              </s:restriction>
            </s:simpleType>
          </s:element>
          <s:element minOccurs="0" name="Zip">
            <s:simpleType>
              <s:restriction base="s:string">
                <s:maxLength value="5"/>
              </s:restriction>
            </s:simpleType>
          </s:element>
        </s:sequence>
      </s:complexType>
      <s:complexType name="ArrayOfFavoriteColorsItemString">
        <s:sequence>
          <s:element maxOccurs="unbounded" minOccurs="0" name="FavoriteColorsItem" nillable="true" type="s:string"/>
        </s:sequence>
      </s:complexType>
      <s:element name="GetByName">
        <s:complexType>
          <s:sequence>
            <s:element minOccurs="0" name="name" type="s:string"/>
          </s:sequence>
        </s:complexType>
      </s:element>
      <s:element name="GetByNameResponse">
        <s:complexType>
          <s:sequence>
            <s:element name="GetByNameResult" type="s0:DataSet"/>
          </s:sequence>
        </s:complexType>
      </s:element>
      <s:complexType name="DataSet">
        <s:sequence>
          <s:element ref="s:schema"/>
          <s:any/>
        </s:sequence>
      </s:complexType>
      <s:element name="GetDataSetByName">
        <s:complexType>
          <s:sequence>
            <s:element minOccurs="0" name="name" type="s:string"/>
          </s:sequence>
        </s:complexType>
      </s:element>
      <s:element name="GetDataSetByNameResponse">
        <s:complexType>
          <s:sequence>
            <s:element name="GetDataSetByNameResult" type="s0:ByNameDataSet"/>
          </s:sequence>
        </s:complexType>
      </s:element>
      <s:complexType name="ByNameDataSet">
        <s:sequence>
          <s:any namespace="http://tempuri.org/ByNameDataSet"/>
        </s:sequence>
      </s:complexType>
      <s:element name="GetListByName">
        <s:complexType>
          <s:sequence>
            <s:element minOccurs="0" name="name" type="s:string"/>
          </s:sequence>
        </s:complexType>
      </s:element>
      <s:element name="GetListByNameResponse">
        <s:complexType>
          <s:sequence>
            <s:element name="GetListByNameResult" type="s0:ArrayOfPersonIdentificationPersonIdentification"/>
          </s:sequence>
        </s:complexType>
      </s:element>
      <s:complexType name="ArrayOfPersonIdentificationPersonIdentification">
        <s:sequence>
          <s:element maxOccurs="unbounded" minOccurs="0" name="PersonIdentification" nillable="true" type="s0:PersonIdentification"/>
        </s:sequence>
      </s:complexType>
      <s:complexType name="PersonIdentification">
        <s:sequence>
          <s:element minOccurs="0" name="ID" type="s:string"/>
          <s:element name="Name" type="s:string"/>
          <s:element name="SSN" type="s:string"/>
          <s:element minOccurs="0" name="DOB" type="s:date"/>
        </s:sequence>
      </s:complexType>
      <s:element name="LookupCity">
        <s:complexType>
          <s:sequence>
            <s:element minOccurs="0" name="zip" type="s:string"/>
          </s:sequence>
        </s:complexType>
      </s:element>
      <s:element name="LookupCityResponse">
        <s:complexType>
          <s:sequence>
            <s:element name="LookupCityResult" type="s0:Address"/>
          </s:sequence>
        </s:complexType>
      </s:element>
      <s:element name="Mission">
        <s:complexType>
          <s:sequence/>
        </s:complexType>
      </s:element>
      <s:element name="MissionResponse">
        <s:complexType>
          <s:sequence>
            <s:element name="MissionResult" type="s:string"/>
          </s:sequence>
        </s:complexType>
      </s:element>
      <s:element name="QueryByName">
        <s:complexType>
          <s:sequence>
            <s:element minOccurs="0" name="name" type="s:string"/>
          </s:sequence>
        </s:complexType>
      </s:element>
      <s:element name="QueryByNameResponse">
        <s:complexType>
          <s:sequence>
            <s:element name="QueryByNameResult" type="s0:QueryByName_DataSet"/>
          </s:sequence>
        </s:complexType>
      </s:element>
      <s:complexType name="QueryByName_DataSet">
        <s:sequence>
          <s:any namespace="http://tempuri.org/QueryByName_DataSet"/>
        </s:sequence>
      </s:complexType>
    </s:schema>
  </types>
  <message name="AddIntegerSoapIn">
    <part name="parameters" element="s0:AddInteger"/>
  </message>
  <message name="AddIntegerSoapOut">
    <part name="parameters" element="s0:AddIntegerResponse"/>
  </message>
  <message name="DivideIntegerSoapIn">
    <part name="parameters" element="s0:DivideInteger"/>
  </message>
  <message name="DivideIntegerSoapOut">
    <part name="parameters" element="s0:DivideIntegerResponse"/>
  </message>
  <message name="FindPersonSoapIn">
    <part name="parameters" element="s0:FindPerson"/>
  </message>
  <message name="FindPersonSoapOut">
    <part name="parameters" element="s0:FindPersonResponse"/>
  </message>
  <message name="GetByNameSoapIn">
    <part name="parameters" element="s0:GetByName"/>
  </message>
  <message name="GetByNameSoapOut">
    <part name="parameters" element="s0:GetByNameResponse"/>
  </message>
  <message name="GetDataSetByNameSoapIn">
    <part name="parameters" element="s0:GetDataSetByName"/>
  </message>
  <message name="GetDataSetByNameSoapOut">
    <part name="parameters" element="s0:GetDataSetByNameResponse"/>
  </message>
  <message name="GetListByNameSoapIn">
    <part name="parameters" element="s0:GetListByName"/>
  </message>
  <message name="GetListByNameSoapOut">
    <part name="parameters" element="s0:GetListByNameResponse"/>
  </message>
  <message name="LookupCitySoapIn">
    <part name="parameters" element="s0:LookupCity"/>
  </message>
  <message name="LookupCitySoapOut">
    <part name="parameters" element="s0:LookupCityResponse"/>
  </message>
  <message name="MissionSoapIn">
    <part name="parameters" element="s0:Mission"/>
  </message>
  <message name="MissionSoapOut">
    <part name="parameters" element="s0:MissionResponse"/>
  </message>
  <message name="QueryByNameSoapIn">
    <part name="parameters" element="s0:QueryByName"/>
  </message>
  <message name="QueryByNameSoapOut">
    <part name="parameters" element="s0:QueryByNameResponse"/>
  </message>
  <portType name="SOAPDemoSoap">
    <operation name="AddInteger">
      <input message="s0:AddIntegerSoapIn"/>
      <output message="s0:AddIntegerSoapOut"/>
    </operation>
    <operation name="DivideInteger">
      <input message="s0:DivideIntegerSoapIn"/>
      <output message="s0:DivideIntegerSoapOut"/>
    </operation>
    <operation name="FindPerson">
      <input message="s0:FindPersonSoapIn"/>
      <output message="s0:FindPersonSoapOut"/>
    </operation>
    <operation name="GetByName">
      <input message="s0:GetByNameSoapIn"/>
      <output message="s0:GetByNameSoapOut"/>
    </operation>
    <operation name="GetDataSetByName">
      <input message="s0:GetDataSetByNameSoapIn"/>
      <output message="s0:GetDataSetByNameSoapOut"/>
    </operation>
    <operation name="GetListByName">
      <input message="s0:GetListByNameSoapIn"/>
      <output message="s0:GetListByNameSoapOut"/>
    </operation>
    <operation name="LookupCity">
      <input message="s0:LookupCitySoapIn"/>
      <output message="s0:LookupCitySoapOut"/>
    </operation>
    <operation name="Mission">
      <input message="s0:MissionSoapIn"/>
      <output message="s0:MissionSoapOut"/>
    </operation>
    <operation name="QueryByName">
      <input message="s0:QueryByNameSoapIn"/>
      <output message="s0:QueryByNameSoapOut"/>
    </operation>
  </portType>
  <binding name="SOAPDemoSoap" type="s0:SOAPDemoSoap">
    <soap:binding transport="http://schemas.xmlsoap.org/soap/http" style="document"/>
    <operation name="AddInteger">
      <soap:operation soapAction="http://tempuri.org/SOAP.Demo.AddInteger" style="document"/>
      <input>
        <soap:body use="literal"/>
      </input>
      <output>
        <soap:body use="literal"/>
      </output>
    </operation>
    <operation name="DivideInteger">
      <soap:operation soapAction="http://tempuri.org/SOAP.Demo.DivideInteger" style="document"/>
      <input>
        <soap:body use="literal"/>
      </input>
      <output>
        <soap:body use="literal"/>
      </output>
    </operation>
    <operation name="FindPerson">
      <soap:operation soapAction="http://tempuri.org/SOAP.Demo.FindPerson" style="document"/>
      <input>
        <soap:body use="literal"/>
      </input>
      <output>
        <soap:body use="literal"/>
      </output>
    </operation>
    <operation name="GetByName">
      <soap:operation soapAction="http://tempuri.org/SOAP.Demo.GetByName" style="document"/>
      <input>
        <soap:body use="literal"/>
      </input>
      <output>
        <soap:body use="literal"/>
      </output>
    </operation>
    <operation name="GetDataSetByName">
      <soap:operation soapAction="http://tempuri.org/SOAP.Demo.GetDataSetByName" style="document"/>
      <input>
        <soap:body use="literal"/>
      </input>
      <output>
        <soap:body use="literal"/>
      </output>
    </operation>
    <operation name="GetListByName">
      <soap:operation soapAction="http://tempuri.org/SOAP.Demo.GetListByName" style="document"/>
      <input>
        <soap:body use="literal"/>
      </input>
      <output>
        <soap:body use="literal"/>
      </output>
    </operation>
    <operation name="LookupCity">
      <soap:operation soapAction="http://tempuri.org/SOAP.Demo.LookupCity" style="document"/>
      <input>
        <soap:body use="literal"/>
      </input>
      <output>
        <soap:body use="literal"/>
      </output>
    </operation>
    <operation name="Mission">
      <soap:operation soapAction="http://tempuri.org/SOAP.Demo.Mission" style="document"/>
      <input>
        <soap:body use="literal"/>
      </input>
      <output>
        <soap:body use="literal"/>
      </output>
    </operation>
    <operation name="QueryByName">
      <soap:operation soapAction="http://tempuri.org/SOAP.Demo.QueryByName" style="document"/>
      <input>
        <soap:body use="literal"/>
      </input>
      <output>
        <soap:body use="literal"/>
      </output>
    </operation>
  </binding>
  <service name="SOAPDemo">
    <port name="SOAPDemoSoap" binding="s0:SOAPDemoSoap">
      <soap:address location="https://www.crcind.com:443/csp/samples/SOAP.Demo.cls"/>
    </port>
  </service>
</definitions>]]></con:content><con:type>http://schemas.xmlsoap.org/wsdl/</con:type></con:part><con:part><con:url>https://www.crcind.com:443/csp/samples/SOAP.ByNameDataSet.cls?XSD</con:url><con:content><![CDATA[<s:schema id="ByNameDataSet" targetNamespace="http://tempuri.org/ByNameDataSet" attributeFormDefault="qualified" elementFormDefault="qualified" xmlns="http://tempuri.org/ByNameDataSet" xmlns:mstns="http://tempuri.org/ByNameDataSet" xmlns:s="http://www.w3.org/2001/XMLSchema" xmlns:msdata="urn:schemas-microsoft-com:xml-msdata">
  <s:element name="ByNameDataSet" msdata:IsDataSet="true">
    <s:complexType>
      <s:choice maxOccurs="unbounded">
        <s:element name="ByName">
          <s:complexType>
            <s:sequence>
              <s:element name="ID" type="s:long" minOccurs="0"/>
              <s:element name="Name" type="s:string" minOccurs="0"/>
              <s:element name="DOB" type="s:date" minOccurs="0"/>
              <s:element name="SSN" type="s:string" minOccurs="0"/>
            </s:sequence>
          </s:complexType>
        </s:element>
      </s:choice>
    </s:complexType>
    <s:unique name="Constraint1" msdata:PrimaryKey="true">
      <s:selector xpath=".//mstns:ByName"/>
      <s:field xpath="mstns:ID"/>
    </s:unique>
  </s:element>
</s:schema>]]></con:content><con:type>http://www.w3.org/2001/XMLSchema</con:type></con:part><con:part><con:url>https://www.crcind.com:443/csp/samples/SOAP.Demo.QueryByName.DS.cls?XSD</con:url><con:content><![CDATA[<s:schema id="QueryByName_DataSet" targetNamespace="http://tempuri.org/QueryByName_DataSet" attributeFormDefault="qualified" elementFormDefault="qualified" xmlns="http://tempuri.org/QueryByName_DataSet" xmlns:mstns="http://tempuri.org/QueryByName_DataSet" xmlns:s="http://www.w3.org/2001/XMLSchema" xmlns:msdata="urn:schemas-microsoft-com:xml-msdata">
  <s:element name="QueryByName_DataSet" msdata:IsDataSet="true">
    <s:complexType>
      <s:choice maxOccurs="unbounded">
        <s:element name="QueryByName">
          <s:complexType>
            <s:sequence>
              <s:element name="ID" type="s:long" minOccurs="0"/>
              <s:element name="Name" type="s:string" minOccurs="0"/>
              <s:element name="DOB" type="s:date" minOccurs="0"/>
              <s:element name="SSN" type="s:string" minOccurs="0"/>
            </s:sequence>
          </s:complexType>
        </s:element>
      </s:choice>
    </s:complexType>
    <s:unique name="Constraint1" msdata:PrimaryKey="true">
      <s:selector xpath=".//mstns:QueryByName"/>
      <s:field xpath="mstns:ID"/>
    </s:unique>
  </s:element>
</s:schema>]]></con:content><con:type>http://www.w3.org/2001/XMLSchema</con:type></con:part></con:definitionCache><con:endpoints><con:endpoint>https://www.crcind.com:443/csp/samples/SOAP.Demo.cls</con:endpoint></con:endpoints><con:operation id="4d1f55b1-141f-4fc2-94a4-47a1e7f26044" isOneWay="false" action="http://tempuri.org/SOAP.Demo.AddInteger" name="AddInteger" bindingOperationName="AddInteger" type="Request-Response" inputName="" receivesAttachments="false" sendsAttachments="false" anonymous="optional"><con:settings/><con:call id="ebed85e1-2097-4d0f-a710-0c118063e3bf" name="Request 1"><con:settings/><con:encoding>UTF-8</con:encoding><con:endpoint>https://www.crcind.com:443/csp/samples/SOAP.Demo.cls</con:endpoint><con:request><![CDATA[<soapenv:Envelope xmlns:soapenv="http://schemas.xmlsoap.org/soap/envelope/" xmlns:tem="http://tempuri.org">\r
   <soapenv:Header/>\r
   <soapenv:Body>\r
      <tem:AddInteger>\r
         <!--Optional:-->\r
         <tem:Arg1>?</tem:Arg1>\r
         <!--Optional:-->\r
         <tem:Arg2>?</tem:Arg2>\r
      </tem:AddInteger>\r
   </soapenv:Body>\r
</soapenv:Envelope>]]></con:request><con:credentials><con:authType>No Authorization</con:authType></con:credentials><con:jmsConfig JMSDeliveryMode="PERSISTENT"/><con:jmsPropertyConfig/><con:wsaConfig mustUnderstand="NONE" version="200508" action="http://tempuri.org/SOAP.Demo.AddInteger"/><con:wsrmConfig version="1.2"/></con:call></con:operation><con:operation id="bd74e273-0443-47f1-83c5-11facf78463c" isOneWay="false" action="http://tempuri.org/SOAP.Demo.DivideInteger" name="DivideInteger" bindingOperationName="DivideInteger" type="Request-Response" inputName="" receivesAttachments="false" sendsAttachments="false" anonymous="optional"><con:settings/><con:call id="890a7115-b808-4cb3-a27f-c5fbb119152a" name="Request 1"><con:settings/><con:encoding>UTF-8</con:encoding><con:endpoint>https://www.crcind.com:443/csp/samples/SOAP.Demo.cls</con:endpoint><con:request><![CDATA[<soapenv:Envelope xmlns:soapenv="http://schemas.xmlsoap.org/soap/envelope/" xmlns:tem="http://tempuri.org">\r
   <soapenv:Header/>\r
   <soapenv:Body>\r
      <tem:DivideInteger>\r
         <!--Optional:-->\r
         <tem:Arg1>?</tem:Arg1>\r
         <!--Optional:-->\r
         <tem:Arg2>?</tem:Arg2>\r
      </tem:DivideInteger>\r
   </soapenv:Body>\r
</soapenv:Envelope>]]></con:request><con:wsaConfig mustUnderstand="NONE" version="200508" action="http://tempuri.org/SOAP.Demo.DivideInteger"/></con:call></con:operation><con:operation id="80518d60-c7a9-4e6d-939b-cc6fd383f492" isOneWay="false" action="http://tempuri.org/SOAP.Demo.FindPerson" name="FindPerson" bindingOperationName="FindPerson" type="Request-Response" inputName="" receivesAttachments="false" sendsAttachments="false" anonymous="optional"><con:settings/><con:call id="f8f1fdde-2fd5-44b2-9877-ab4d34b9beb7" name="Request 1"><con:settings/><con:encoding>UTF-8</con:encoding><con:endpoint>https://www.crcind.com:443/csp/samples/SOAP.Demo.cls</con:endpoint><con:request><![CDATA[<soapenv:Envelope xmlns:soapenv="http://schemas.xmlsoap.org/soap/envelope/" xmlns:tem="http://tempuri.org">\r
   <soapenv:Header/>\r
   <soapenv:Body>\r
      <tem:FindPerson>\r
         <!--Optional:-->\r
         <tem:id>?</tem:id>\r
      </tem:FindPerson>\r
   </soapenv:Body>\r
</soapenv:Envelope>]]></con:request><con:wsaConfig mustUnderstand="NONE" version="200508" action="http://tempuri.org/SOAP.Demo.FindPerson"/></con:call></con:operation><con:operation id="618e452b-9f15-4b62-962d-a39be73813bd" isOneWay="false" action="http://tempuri.org/SOAP.Demo.GetByName" name="GetByName" bindingOperationName="GetByName" type="Request-Response" inputName="" receivesAttachments="false" sendsAttachments="false" anonymous="optional"><con:settings/><con:call id="eff93eae-6257-498a-a940-6a4f59294af8" name="Request 1"><con:settings/><con:encoding>UTF-8</con:encoding><con:endpoint>https://www.crcind.com:443/csp/samples/SOAP.Demo.cls</con:endpoint><con:request><![CDATA[<soapenv:Envelope xmlns:soapenv="http://schemas.xmlsoap.org/soap/envelope/" xmlns:tem="http://tempuri.org">\r
   <soapenv:Header/>\r
   <soapenv:Body>\r
      <tem:GetByName>\r
         <!--Optional:-->\r
         <tem:name>?</tem:name>\r
      </tem:GetByName>\r
   </soapenv:Body>\r
</soapenv:Envelope>]]></con:request><con:wsaConfig mustUnderstand="NONE" version="200508" action="http://tempuri.org/SOAP.Demo.GetByName"/></con:call></con:operation><con:operation id="6a1c35e6-2162-4966-b10e-ce688713e06e" isOneWay="false" action="http://tempuri.org/SOAP.Demo.GetDataSetByName" name="GetDataSetByName" bindingOperationName="GetDataSetByName" type="Request-Response" inputName="" receivesAttachments="false" sendsAttachments="false" anonymous="optional"><con:settings/><con:call id="0c11cd74-aefc-47c0-96ba-0773e2072be9" name="Request 1"><con:settings/><con:encoding>UTF-8</con:encoding><con:endpoint>https://www.crcind.com:443/csp/samples/SOAP.Demo.cls</con:endpoint><con:request><![CDATA[<soapenv:Envelope xmlns:soapenv="http://schemas.xmlsoap.org/soap/envelope/" xmlns:tem="http://tempuri.org">\r
   <soapenv:Header/>\r
   <soapenv:Body>\r
      <tem:GetDataSetByName>\r
         <!--Optional:-->\r
         <tem:name>?</tem:name>\r
      </tem:GetDataSetByName>\r
   </soapenv:Body>\r
</soapenv:Envelope>]]></con:request><con:wsaConfig mustUnderstand="NONE" version="200508" action="http://tempuri.org/SOAP.Demo.GetDataSetByName"/></con:call></con:operation><con:operation id="79f03bd9-d7c7-415f-952f-2213f84bc2b3" isOneWay="false" action="http://tempuri.org/SOAP.Demo.GetListByName" name="GetListByName" bindingOperationName="GetListByName" type="Request-Response" inputName="" receivesAttachments="false" sendsAttachments="false" anonymous="optional"><con:settings/><con:call id="07f4b514-5e91-42dd-a18f-e5ef57de2fd8" name="Request 1"><con:settings/><con:encoding>UTF-8</con:encoding><con:endpoint>https://www.crcind.com:443/csp/samples/SOAP.Demo.cls</con:endpoint><con:request><![CDATA[<soapenv:Envelope xmlns:soapenv="http://schemas.xmlsoap.org/soap/envelope/" xmlns:tem="http://tempuri.org">\r
   <soapenv:Header/>\r
   <soapenv:Body>\r
      <tem:GetListByName>\r
         <!--Optional:-->\r
         <tem:name>?</tem:name>\r
      </tem:GetListByName>\r
   </soapenv:Body>\r
</soapenv:Envelope>]]></con:request><con:wsaConfig mustUnderstand="NONE" version="200508" action="http://tempuri.org/SOAP.Demo.GetListByName"/></con:call></con:operation><con:operation id="820ac52c-c1b3-4980-9e7b-4e74f47b4cba" isOneWay="false" action="http://tempuri.org/SOAP.Demo.LookupCity" name="LookupCity" bindingOperationName="LookupCity" type="Request-Response" inputName="" receivesAttachments="false" sendsAttachments="false" anonymous="optional"><con:settings/><con:call id="5a1ab885-b052-4651-9a30-dedb86c5cfa6" name="Request 1"><con:settings/><con:encoding>UTF-8</con:encoding><con:endpoint>https://www.crcind.com:443/csp/samples/SOAP.Demo.cls</con:endpoint><con:request><![CDATA[<soapenv:Envelope xmlns:soapenv="http://schemas.xmlsoap.org/soap/envelope/" xmlns:tem="http://tempuri.org">\r
   <soapenv:Header/>\r
   <soapenv:Body>\r
      <tem:LookupCity>\r
         <!--Optional:-->\r
         <tem:zip>?</tem:zip>\r
      </tem:LookupCity>\r
   </soapenv:Body>\r
</soapenv:Envelope>]]></con:request><con:wsaConfig mustUnderstand="NONE" version="200508" action="http://tempuri.org/SOAP.Demo.LookupCity"/></con:call></con:operation><con:operation id="cefeeb3a-4020-44f5-9180-c2f656e041f2" isOneWay="false" action="http://tempuri.org/SOAP.Demo.Mission" name="Mission" bindingOperationName="Mission" type="Request-Response" inputName="" receivesAttachments="false" sendsAttachments="false" anonymous="optional"><con:settings/><con:call id="b7f235c4-f3a5-4672-9afe-6bfe15e639f6" name="Request 1"><con:settings/><con:encoding>UTF-8</con:encoding><con:endpoint>https://www.crcind.com:443/csp/samples/SOAP.Demo.cls</con:endpoint><con:request><![CDATA[<soapenv:Envelope xmlns:soapenv="http://schemas.xmlsoap.org/soap/envelope/" xmlns:tem="http://tempuri.org">\r
   <soapenv:Header/>\r
   <soapenv:Body>\r
      <tem:Mission/>\r
   </soapenv:Body>\r
</soapenv:Envelope>]]></con:request><con:wsaConfig mustUnderstand="NONE" version="200508" action="http://tempuri.org/SOAP.Demo.Mission"/></con:call></con:operation><con:operation id="cfa99506-698d-48f5-9a18-d01be9eab97e" isOneWay="false" action="http://tempuri.org/SOAP.Demo.QueryByName" name="QueryByName" bindingOperationName="QueryByName" type="Request-Response" inputName="" receivesAttachments="false" sendsAttachments="false" anonymous="optional"><con:settings/><con:call id="68d0de84-6d4e-4c71-89f8-ec76ac0ac163" name="Request 1"><con:settings/><con:encoding>UTF-8</con:encoding><con:endpoint>https://www.crcind.com:443/csp/samples/SOAP.Demo.cls</con:endpoint><con:request><![CDATA[<soapenv:Envelope xmlns:soapenv="http://schemas.xmlsoap.org/soap/envelope/" xmlns:tem="http://tempuri.org">\r
   <soapenv:Header/>\r
   <soapenv:Body>\r
      <tem:QueryByName>\r
         <!--Optional:-->\r
         <tem:name>?</tem:name>\r
      </tem:QueryByName>\r
   </soapenv:Body>\r
</soapenv:Envelope>]]></con:request><con:wsaConfig mustUnderstand="NONE" version="200508" action="http://tempuri.org/SOAP.Demo.QueryByName"/></con:call></con:operation></con:interface><con:testSuite id="a6a89a9e-7cae-4848-9448-65cfc7aa8dad" name="SOAPDemoSoap TestSuite"><con:settings/><con:runType>SEQUENTIAL</con:runType><con:testCase id="b8faba42-cccc-423a-aa62-89b3e5ac9330" failOnError="true" failTestCaseOnErrors="true" keepSession="false" maxResults="0" name="AddInteger TestCase" searchProperties="true"><con:settings/><con:testStep type="request" name="AddInteger" id="0e057b0e-448f-43b4-9630-5c919537b87a"><con:settings/><con:config xsi:type="con:RequestStep" xmlns:xsi="http://www.w3.org/2001/XMLSchema-instance"><con:interface>SOAPDemoSoap</con:interface><con:operation>AddInteger</con:operation><con:request name="AddInteger" id="ffa297d6-1d9b-49d5-89fd-2318c6a130a5"><con:settings><con:setting id="com.eviware.soapui.impl.wsdl.WsdlRequest@request-headers">&lt;xml-fragment/></con:setting></con:settings><con:encoding>UTF-8</con:encoding><con:endpoint>https://www.crcind.com:443/csp/samples/SOAP.Demo.cls</con:endpoint><con:request><![CDATA[<soapenv:Envelope xmlns:soapenv="http://schemas.xmlsoap.org/soap/envelope/" xmlns:tem="http://tempuri.org">\r
   <soapenv:Header/>\r
   <soapenv:Body>\r
      <tem:AddInteger/>\r
   </soapenv:Body>\r
</soapenv:Envelope>]]></con:request><con:assertion type="SOAP Response" id="3ceefeec-2cf5-48b6-9d35-80eb3f471392"/><con:assertion type="Simple Contains" id="6bc559a4-7c33-45b2-9df1-e65a108134a1" name="Contains"><con:configuration><token>5</token><ignoreCase>false</ignoreCase><useRegEx>false</useRegEx></con:configuration></con:assertion><con:assertion type="Simple Contains"/><con:credentials><con:authType>No Authorization</con:authType></con:credentials><con:jmsConfig JMSDeliveryMode="PERSISTENT"/><con:jmsPropertyConfig/><con:wsaConfig mustUnderstand="NONE" version="200508"/><con:wsrmConfig version="1.2"/></con:request></con:config></con:testStep><con:properties/></con:testCase><con:testCase id="90861718-047e-4b76-a87f-2fbabc74f645" failOnError="true" failTestCaseOnErrors="true" keepSession="false" maxResults="0" name="DivideInteger TestCase" searchProperties="true"><con:settings/><con:testStep type="request" id="352d03ac-1955-44ed-bc65-470ed5b2b333" name="DivideInteger"><con:settings/><con:config xsi:type="con:RequestStep" xmlns:xsi="http://www.w3.org/2001/XMLSchema-instance"><con:interface>SOAPDemoSoap</con:interface><con:operation>DivideInteger</con:operation><con:request name="DivideInteger" id="6f347b92-b3f8-4d78-bb9b-b1efd731cc9c"><con:settings/><con:encoding>UTF-8</con:encoding><con:endpoint>https://www.crcind.com:443/csp/samples/SOAP.Demo.cls</con:endpoint><con:request><![CDATA[<soapenv:Envelope xmlns:soapenv="http://schemas.xmlsoap.org/soap/envelope/" xmlns:tem="http://tempuri.org">\r
   <soapenv:Header/>\r
   <soapenv:Body>\r
      <tem:DivideInteger>\r
         <!--Optional:-->\r
         <tem:Arg1>?</tem:Arg1>\r
         <!--Optional:-->\r
         <tem:Arg2>?</tem:Arg2>\r
      </tem:DivideInteger>\r
   </soapenv:Body>\r
</soapenv:Envelope>]]></con:request><con:credentials><con:authType>No Authorization</con:authType></con:credentials><con:wsaConfig action="http://tempuri.org/SOAP.Demo.DivideInteger"/></con:request></con:config></con:testStep><con:properties/></con:testCase><con:testCase id="566ea60e-1f51-4380-afa2-6c13cf95dd59" failOnError="true" failTestCaseOnErrors="true" keepSession="false" maxResults="0" name="FindPerson TestCase" searchProperties="true"><con:settings/><con:testStep type="request" id="8c5657fe-86e6-4dfd-8ffd-05eff876f59d" name="FindPerson"><con:settings/><con:config xsi:type="con:RequestStep" xmlns:xsi="http://www.w3.org/2001/XMLSchema-instance"><con:interface>SOAPDemoSoap</con:interface><con:operation>FindPerson</con:operation><con:request name="FindPerson" id="d69e90d8-33bd-4566-a324-26c68ab90f25"><con:settings/><con:encoding>UTF-8</con:encoding><con:endpoint>https://www.crcind.com:443/csp/samples/SOAP.Demo.cls</con:endpoint><con:request><![CDATA[<soapenv:Envelope xmlns:soapenv="http://schemas.xmlsoap.org/soap/envelope/" xmlns:tem="http://tempuri.org">\r
   <soapenv:Header/>\r
   <soapenv:Body>\r
      <tem:FindPerson>\r
         <!--Optional:-->\r
         <tem:id>?</tem:id>\r
      </tem:FindPerson>\r
   </soapenv:Body>\r
</soapenv:Envelope>]]></con:request><con:credentials><con:authType>No Authorization</con:authType></con:credentials><con:wsaConfig action="http://tempuri.org/SOAP.Demo.FindPerson"/></con:request></con:config></con:testStep><con:properties/></con:testCase><con:testCase id="5c092d6d-c11e-4dac-a9a2-4359ef9798ef" failOnError="true" failTestCaseOnErrors="true" keepSession="false" maxResults="0" name="GetByName TestCase" searchProperties="true"><con:settings/><con:testStep type="request" id="23685cd7-f68e-4853-9a82-d66733395cb8" name="GetByName"><con:settings/><con:config xsi:type="con:RequestStep" xmlns:xsi="http://www.w3.org/2001/XMLSchema-instance"><con:interface>SOAPDemoSoap</con:interface><con:operation>GetByName</con:operation><con:request name="GetByName" id="9f088d48-e87a-45c7-b527-02f2efb40832"><con:settings/><con:encoding>UTF-8</con:encoding><con:endpoint>https://www.crcind.com:443/csp/samples/SOAP.Demo.cls</con:endpoint><con:request><![CDATA[<soapenv:Envelope xmlns:soapenv="http://schemas.xmlsoap.org/soap/envelope/" xmlns:tem="http://tempuri.org">\r
   <soapenv:Header/>\r
   <soapenv:Body>\r
      <tem:GetByName>\r
         <!--Optional:-->\r
         <tem:name>?</tem:name>\r
      </tem:GetByName>\r
   </soapenv:Body>\r
</soapenv:Envelope>]]></con:request><con:credentials><con:authType>No Authorization</con:authType></con:credentials><con:wsaConfig action="http://tempuri.org/SOAP.Demo.GetByName"/></con:request></con:config></con:testStep><con:properties/></con:testCase><con:testCase id="4d6debc9-c10a-41e2-a3fb-dff5ff3c7571" failOnError="true" failTestCaseOnErrors="true" keepSession="false" maxResults="0" name="GetDataSetByName TestCase" searchProperties="true"><con:settings/><con:testStep type="request" id="ed125cbd-7d5f-40ed-afd2-7aa4edd22249" name="GetDataSetByName"><con:settings/><con:config xsi:type="con:RequestStep" xmlns:xsi="http://www.w3.org/2001/XMLSchema-instance"><con:interface>SOAPDemoSoap</con:interface><con:operation>GetDataSetByName</con:operation><con:request name="GetDataSetByName" id="643bfd19-4791-48e8-87b4-4559f90242a2"><con:settings/><con:encoding>UTF-8</con:encoding><con:endpoint>https://www.crcind.com:443/csp/samples/SOAP.Demo.cls</con:endpoint><con:request><![CDATA[<soapenv:Envelope xmlns:soapenv="http://schemas.xmlsoap.org/soap/envelope/" xmlns:tem="http://tempuri.org">\r
   <soapenv:Header/>\r
   <soapenv:Body>\r
      <tem:GetDataSetByName>\r
         <!--Optional:-->\r
         <tem:name>?</tem:name>\r
      </tem:GetDataSetByName>\r
   </soapenv:Body>\r
</soapenv:Envelope>]]></con:request><con:credentials><con:authType>No Authorization</con:authType></con:credentials><con:wsaConfig action="http://tempuri.org/SOAP.Demo.GetDataSetByName"/></con:request></con:config></con:testStep><con:properties/></con:testCase><con:testCase id="7d55a8a8-d216-4eaa-bcd7-14309bcba34a" failOnError="true" failTestCaseOnErrors="true" keepSession="false" maxResults="0" name="GetListByName TestCase" searchProperties="true"><con:settings/><con:testStep type="request" id="19ea178a-2a0c-4cc6-a3bd-b54763599e3c" name="GetListByName"><con:settings/><con:config xsi:type="con:RequestStep" xmlns:xsi="http://www.w3.org/2001/XMLSchema-instance"><con:interface>SOAPDemoSoap</con:interface><con:operation>GetListByName</con:operation><con:request name="GetListByName" id="0740ae67-6620-49d5-992a-43b3cc4d087e"><con:settings/><con:encoding>UTF-8</con:encoding><con:endpoint>https://www.crcind.com:443/csp/samples/SOAP.Demo.cls</con:endpoint><con:request><![CDATA[<soapenv:Envelope xmlns:soapenv="http://schemas.xmlsoap.org/soap/envelope/" xmlns:tem="http://tempuri.org">\r
   <soapenv:Header/>\r
   <soapenv:Body>\r
      <tem:GetListByName>\r
         <!--Optional:-->\r
         <tem:name>?</tem:name>\r
      </tem:GetListByName>\r
   </soapenv:Body>\r
</soapenv:Envelope>]]></con:request><con:credentials><con:authType>No Authorization</con:authType></con:credentials><con:wsaConfig action="http://tempuri.org/SOAP.Demo.GetListByName"/></con:request></con:config></con:testStep><con:properties/></con:testCase><con:testCase id="39224532-1061-4e68-b659-be0fba5581c3" failOnError="true" failTestCaseOnErrors="true" keepSession="false" maxResults="0" name="LookupCity TestCase" searchProperties="true"><con:settings/><con:testStep type="request" id="cc548bd2-88da-40e2-aeab-3277c29e9d33" name="LookupCity"><con:settings/><con:config xsi:type="con:RequestStep" xmlns:xsi="http://www.w3.org/2001/XMLSchema-instance"><con:interface>SOAPDemoSoap</con:interface><con:operation>LookupCity</con:operation><con:request name="LookupCity" id="252e985c-7417-4ddf-a99c-0de0488c01bf"><con:settings/><con:encoding>UTF-8</con:encoding><con:endpoint>https://www.crcind.com:443/csp/samples/SOAP.Demo.cls</con:endpoint><con:request><![CDATA[<soapenv:Envelope xmlns:soapenv="http://schemas.xmlsoap.org/soap/envelope/" xmlns:tem="http://tempuri.org">\r
   <soapenv:Header/>\r
   <soapenv:Body>\r
      <tem:LookupCity>\r
         <!--Optional:-->\r
         <tem:zip>?</tem:zip>\r
      </tem:LookupCity>\r
   </soapenv:Body>\r
</soapenv:Envelope>]]></con:request><con:credentials><con:authType>No Authorization</con:authType></con:credentials><con:wsaConfig action="http://tempuri.org/SOAP.Demo.LookupCity"/></con:request></con:config></con:testStep><con:properties/></con:testCase><con:testCase id="742ba5fe-65c4-4fd3-ad8a-8ba531540efb" failOnError="true" failTestCaseOnErrors="true" keepSession="false" maxResults="0" name="Mission TestCase" searchProperties="true"><con:settings/><con:testStep type="request" id="da0bac5e-0fc6-46fe-9996-e0b52839e6a2" name="Mission"><con:settings/><con:config xsi:type="con:RequestStep" xmlns:xsi="http://www.w3.org/2001/XMLSchema-instance"><con:interface>SOAPDemoSoap</con:interface><con:operation>Mission</con:operation><con:request name="Mission" id="34714bb6-bd20-483e-905e-0acfca966f55"><con:settings/><con:encoding>UTF-8</con:encoding><con:endpoint>https://www.crcind.com:443/csp/samples/SOAP.Demo.cls</con:endpoint><con:request><![CDATA[<soapenv:Envelope xmlns:soapenv="http://schemas.xmlsoap.org/soap/envelope/" xmlns:tem="http://tempuri.org">\r
   <soapenv:Header/>\r
   <soapenv:Body>\r
      <tem:Mission/>\r
   </soapenv:Body>\r
</soapenv:Envelope>]]></con:request><con:credentials><con:authType>No Authorization</con:authType></con:credentials><con:wsaConfig action="http://tempuri.org/SOAP.Demo.Mission"/></con:request></con:config></con:testStep><con:properties/></con:testCase><con:testCase id="80d6b113-a4b3-47c2-ab95-47ccd53cd8d5" failOnError="true" failTestCaseOnErrors="true" keepSession="false" maxResults="0" name="QueryByName TestCase" searchProperties="true"><con:settings/><con:testStep type="request" id="0b4beed2-acca-47e8-bbce-7592dea89f77" name="QueryByName"><con:settings/><con:config xsi:type="con:RequestStep" xmlns:xsi="http://www.w3.org/2001/XMLSchema-instance"><con:interface>SOAPDemoSoap</con:interface><con:operation>QueryByName</con:operation><con:request name="QueryByName" id="719fb00c-a71d-41fa-819c-583f32acc3b4"><con:settings/><con:encoding>UTF-8</con:encoding><con:endpoint>https://www.crcind.com:443/csp/samples/SOAP.Demo.cls</con:endpoint><con:request><![CDATA[<soapenv:Envelope xmlns:soapenv="http://schemas.xmlsoap.org/soap/envelope/" xmlns:tem="http://tempuri.org">\r
   <soapenv:Header/>\r
   <soapenv:Body>\r
      <tem:QueryByName>\r
         <!--Optional:-->\r
         <tem:name>?</tem:name>\r
      </tem:QueryByName>\r
   </soapenv:Body>\r
</soapenv:Envelope>]]></con:request><con:credentials><con:authType>No Authorization</con:authType></con:credentials><con:wsaConfig action="http://tempuri.org/SOAP.Demo.QueryByName"/></con:request></con:config></con:testStep><con:properties/></con:testCase><con:properties/></con:testSuite><con:properties/><con:wssContainer/><con:oAuth2ProfileContainer/><con:oAuth1ProfileContainer/></con:soapui-project>